Metadata-Version: 1.0
Name: lazy-write
Version: 0.0.1
Summary: Write to file if need
Home-page: https://github.com/FebruaryBreeze/lazy-write
Author: SF-Zhou
Author-email: sfzhou.scut@gmail.com
License: UNKNOWN
Keywords: File Read Write
Platform: UNKNOWN
